buildscad/__init__.py
buildscad/__main__.py
buildscad/_test.py
buildscad/blocks.py
buildscad/env.py
buildscad/globals.py
buildscad/main.py
buildscad/openscad.peg
buildscad/peg.py
buildscad/rules.py
buildscad-0.4.1.dist-info/LICENSE.txt
buildscad-0.4.1.dist-info/METADATA
buildscad-0.4.1.dist-info/WHEEL
buildscad-0.4.1.dist-info/entry_points.txt
buildscad-0.4.1.dist-info/top_level.txt
buildscad-0.4.1.dist-info/RECORD
