Metadata-Version: 2.1
Name: buildscad
Version: 0.4.1
Summary: An interpreter for OpenSCAD that renders to build123d objects
Author-email: Matthias Urlichs <matthias@urlichs.de>
License: All files in this repository are are licensed under the LGPL V3, as
Project-URL: homepage, https://github.org/smurfix/buildscad
Project-URL: repository, https://github.com/smurfix/buildscad.git
Keywords: buildscad,cadquery,build123d
Classifier: Intended Audience :: Developers
Classifier: Programming Language :: Python :: 3
Classifier: License :: OSI Approved
Classifier: Development Status :: 3 - Alpha
Requires-Python: >=3.10
License-File: LICENSE.txt
Requires-Dist: build123d
Requires-Dist: click
Requires-Dist: simple-eval
